k3s_control_ao/__init__.py
k3s_control_ao/version.py
k3s_control_ao/application/__init__.py
k3s_control_ao/application/assembler.py
k3s_control_ao/application/dto.py
k3s_control_ao/domain/__init__.py
k3s_control_ao/domain/entity.py
k3s_control_ao/domain/value_obj.py
k3s_control_ao/infrastructure/__init__.py
k3s_control_ao/infrastructure/ao.py
k3s_control_ao/infrastructure/converter.py
k3s_control_ao/infrastructure/do.py
k3s_control_ao-0.2.9.dist-info/LICENSE
k3s_control_ao-0.2.9.dist-info/METADATA
k3s_control_ao-0.2.9.dist-info/WHEEL
k3s_control_ao-0.2.9.dist-info/top_level.txt
k3s_control_ao-0.2.9.dist-info/RECORD
