Metadata-Version: 2.1
Name: k3s-control-ao
Version: 0.2.9
Summary: Exposed interface for accessing k3s controller
Author: wangziling100
Author-email: wangziling100@163.com
Classifier: Programming Language :: Python :: 3
Classifier: License :: OSI Approved :: MIT License
License-File: LICENSE
